setup.py
app_store_ranking_checker/__init__.py
app_store_ranking_checker.egg-info/PKG-INFO
app_store_ranking_checker.egg-info/SOURCES.txt
app_store_ranking_checker.egg-info/dependency_links.txt
app_store_ranking_checker.egg-info/not-zip-safe
app_store_ranking_checker.egg-info/top_level.txt