Metadata-Version: 1.0
Name: app-store-ranking-checker
Version: 0.1
Summary: Check App Store ranking for the given app
Home-page: https://github.com/yuweizhan/app-store-ranking-checker
Author: Yuwei Zhan
Author-email: yzhan@coursehero.com
License: MIT
Platform: UNKNOWN
